klovve/.pylintrc
klovve/__init__.py
klovve/app/__init__.py
klovve/app/runnable.py
klovve/app/tree.py
klovve/builtin/__init__.py
klovve/builtin/drivers/__init__.py
klovve/builtin/drivers/gtk/__init__.py
klovve/builtin/drivers/gtk/loop.py
klovve/builtin/drivers/gtk/-data/main-dark.css
klovve/builtin/drivers/gtk/-data/main-light.css
klovve/builtin/drivers/gtk/-data/main.css
klovve/builtin/drivers/gtk/views/__init__.py
klovve/builtin/drivers/gtk/views/_box.py
klovve/builtin/drivers/gtk/views/busy_animation.py
klovve/builtin/drivers/gtk/views/button.py
klovve/builtin/drivers/gtk/views/check_button.py
klovve/builtin/drivers/gtk/views/dropdown.py
klovve/builtin/drivers/gtk/views/form.py
klovve/builtin/drivers/gtk/views/head_bar.py
klovve/builtin/drivers/gtk/views/horizontal_box.py
klovve/builtin/drivers/gtk/views/label.py
klovve/builtin/drivers/gtk/views/list.py
klovve/builtin/drivers/gtk/views/location_bar.py
klovve/builtin/drivers/gtk/views/log_pager.py
klovve/builtin/drivers/gtk/views/multiline_text_field.py
klovve/builtin/drivers/gtk/views/object_editor.py
klovve/builtin/drivers/gtk/views/placeholder.py
klovve/builtin/drivers/gtk/views/progress_bar.py
klovve/builtin/drivers/gtk/views/scrollable.py
klovve/builtin/drivers/gtk/views/sidebar.py
klovve/builtin/drivers/gtk/views/slider.py
klovve/builtin/drivers/gtk/views/tabbed.py
klovve/builtin/drivers/gtk/views/text_block.py
klovve/builtin/drivers/gtk/views/text_field.py
klovve/builtin/drivers/gtk/views/vertical_box.py
klovve/builtin/drivers/gtk/views/window.py
klovve/builtin/drivers/gtk/views/interact/__init__.py
klovve/builtin/drivers/gtk/views/interact/message.py
klovve/builtin/drivers/gtk/views/interact/text_input.py
klovve/builtin/drivers/gtk/views/responsive/__init__.py
klovve/builtin/drivers/gtk/views/responsive/dual.py
klovve/builtin/drivers/gtk/views/viewer/__init__.py
klovve/builtin/drivers/gtk/views/viewer/image.py
klovve/builtin/drivers/gtk/views/viewer/pdf.py
klovve/builtin/drivers/viwid/__init__.py
klovve-1.6.146.dist-info/METADATA
klovve-1.6.146.dist-info/WHEEL
klovve-1.6.146.dist-info/top_level.txt
klovve-1.6.146.dist-info/RECORD
