Metadata-Version: 2.4
Name: klovve
Version: 1.6.146
Summary: Python User Interfaces
Home-page: https://pseudopolis.eu/pino/klovve
Author: Josef Hahn
Author-email: klovve@pseudopolis.eu
License: AGPL 3
Keywords: python software development ui user interface
Provides-Extra: graphical
Requires-Dist: PyGObject~=3.52; extra == "graphical"
Dynamic: author
Dynamic: author-email
Dynamic: description
Dynamic: description-content-type
Dynamic: home-page
Dynamic: keywords
Dynamic: license
Dynamic: provides-extra
Dynamic: summary
